telemal/Bot.py
telemal/Channel.py
telemal/User.py
telemal/__init__.py
telemal/__main__.py
telemal/telemal.py
telemal-1.2.23.dist-info/licenses/LICENSE
telemal-1.2.23.dist-info/METADATA
telemal-1.2.23.dist-info/WHEEL
telemal-1.2.23.dist-info/entry_points.txt
telemal-1.2.23.dist-info/top_level.txt
telemal-1.2.23.dist-info/RECORD
