Metadata-Version: 2.4
Name: telemal
Version: 1.2.23
Summary: Get intelligence on malicious Telegram channels using bot Token
Home-page: https://github.com/nicolasmf/Telemal
Author: TA1GA
License: MIT
Classifier: Development Status :: 5 - Production/Stable
Classifier: License :: OSI Approved :: MIT License
Classifier: Programming Language :: Python :: 3
License-File: LICENSE
Dynamic: author
Dynamic: classifier
Dynamic: description
Dynamic: description-content-type
Dynamic: home-page
Dynamic: license
Dynamic: license-file
Dynamic: summary
